{
  "project_info": {
    "project_number": "634680639997",
    "project_id": "fireapp-9004c",
    "storage_bucket": "fireapp-9004c.appspot.com"
  },
  "client": [
    {
      "client_info": {
        "mobilesdk_app_id": "1:634680639997:android:2f24d6cf9295cc10099994",
        "android_client_info": {
          "package_name": "com.example.fireapp"
        }
      },
      "oauth_client": [
        {
          "client_id": "634680639997-c285ir90t8a9f6i9liaai23u8qqht5b3.apps.googleusercontent.com",
          "client_type": 3
        }
      ],
      "api_key": [
        {
          "current_key": "AIzaSyDe3E8wBbib18FLCi3FB9JP9Pd5aJw4Zf0"
        }
      ],
      "services": {
        "appinvite_service": {
          "other_platform_oauth_client": [
            {
              "client_id": "634680639997-c285ir90t8a9f6i9liaai23u8qqht5b3.apps.googleusercontent.com",
              "client_type": 3
            }
          ]
        }
      }
    }
  ],
  "configuration_version": "1"
}